{
  "hanzi": "下",
  "pinyin": [
    "xia4"
  ],
  "meanings": [
    "below",
    "down",
    "downwards",
    "later",
    "lower",
    "measure word to show the frequency of an action",
    "next (week etc)",
    "second (of two parts)",
    "to arrive at (a decision, conclusion etc)",
    "to decline",
    "to go down"
  ],
  "hsk_level": 1,
  "frequency": null,
  "structure": {
    "radical": null,
    "components": []
  },
  "strokes": {
    "count": 3,
    "svg": "strokes/svg/19979.svg"
  }
}