{
  "hanzi": "盘",
  "pinyin": [
    "pan2"
  ],
  "meanings": [
    "(computing) (bound form) disk",
    "(finance) (bound form) market prices",
    "classifier for coils",
    "classifier for games or matches (chess, table tennis etc)",
    "classifier for things resembling a plate or dish",
    "to check; to examine; to investigate",
    "to coil (a rope, pigtail etc)",
    "to shift; to move (sth big and heavy)",
    "to transfer; to sell (property)",
    "tray; plate; dish"
  ],
  "hsk_level": 3,
  "frequency": null,
  "structure": {
    "radical": null,
    "components": []
  },
  "strokes": {
    "count": 11,
    "svg": "/strokes/svg/30424.svg"
  }
}
