{
  "hanzi": "那",
  "pinyin": [
    "na1",
    "na3",
    "na4",
    "nuo2"
  ],
  "meanings": [
    "(archaic) many",
    "(pronoun) that (referring to persons, things or situations)",
    "(specifier) that; the; those (colloquial pr. [nei4])",
    "beautiful",
    "how",
    "old variant of 挪[nuo2]",
    "surname Na",
    "surname Nuo",
    "then (in that case)",
    "variant of 哪[na3]"
  ],
  "hsk_level": 1,
  "frequency": null,
  "structure": {
    "radical": null,
    "components": []
  },
  "strokes": {
    "count": 6,
    "svg": "/strokes/svg/37027.svg"
  }
}
