{
  "hanzi": "阿",
  "pinyin": [
    "a1",
    "e1"
  ],
  "meanings": [
    "(literary) to flatter; to curry favor with",
    "abbr. for country names that begin with 阿[a1]: Algeria 阿爾及利亞|阿尔及利亚[A1 er3 ji2 li4 ya4], Afghanistan 阿富汗[A1 fu4 han4] etc",
    "also pr. [a4]",
    "prefix used before monosyllabic names, kinship terms etc to indicate familiarity",
    "used in transliteration"
  ],
  "hsk_level": 3,
  "frequency": null,
  "structure": {
    "radical": null,
    "components": []
  },
  "strokes": {
    "count": 7,
    "svg": "/strokes/svg/38463.svg"
  }
}
